<?xml version="1.0" encoding="UTF-8"?>
<databaseChangeLog
        xmlns="http://www.liquibase.org/xml/ns/dbchangelog/1.7"
        xmlns:xsi="http://www.w3.org/2001/XMLSchema-instance"
        xsi:schemaLocation="http://www.liquibase.org/xml/ns/dbchangelog/1.7
         http://www.liquibase.org/xml/ns/dbchangelog/dbchangelog-1.7.xsd">
    <changeSet author="Elian Kurtev" id="20190518-1">
        <insert schemaName="public"
                tableName="grade">
            <column name="name" value="Intern"/>
        </insert>
        <insert schemaName="public"
                tableName="grade">
            <column name="name" value="Junior"/>
        </insert>
        <insert schemaName="public"
                tableName="grade">
            <column name="name" value="Regular"/>
        </insert>
        <insert schemaName="public"
                tableName="grade">
            <column name="name" value="Expert"/>
        </insert>
        <rollback/>
    </changeSet>
    <changeSet author="Rumyana Krumova" id="20190518-2">
        <insert schemaName="public" tableName="skill">
            <column name="name" value="Java"/>
        </insert>
        <insert schemaName="public" tableName="skill">
            <column name="name" value="C#"/>
        </insert>
        <insert schemaName="public" tableName="skill">
            <column name="name" value="English"/>
        </insert>
        <insert schemaName="public" tableName="skill">
            <column name="name" value="Testing"/>
        </insert>
        <insert schemaName="public" tableName="skill">
            <column name="name" value="Angular"/>
        </insert>
        <insert schemaName="public" tableName="skill">
            <column name="name" value="JavaScript"/>
        </insert>
        <insert schemaName="public" tableName="skill">
            <column name="name" value="Python"/>
        </insert>
        <insert schemaName="public" tableName="skill">
            <column name="name" value="GO"/>
        </insert>
        <insert schemaName="public" tableName="skill">
            <column name="name" value="SpringBoot"/>
        </insert>
        <insert schemaName="public" tableName="skill">
            <column name="name" value="Asp.Net"/>
        </insert>
        <insert schemaName="public" tableName="skill">
            <column name="name" value="C++"/>
        </insert>
        <rollback/>
    </changeSet>
    <changeSet author="Rumyana Krumova" id="20190518-3">
        <insert schemaName="public" tableName="department">
            <column name="name" value="Quality Assurance"/>
        </insert>
        <insert schemaName="public" tableName="department">
            <column name="name" value="Development"/>
        </insert>
        <insert schemaName="public" tableName="department">
            <column name="name" value="Application Management"/>
        </insert>
        <insert schemaName="public" tableName="department">
            <column name="name" value="Management"/>
        </insert>
        <insert schemaName="public" tableName="department">
            <column name="name" value="Human Resources"/>
        </insert>
        <rollback/>
    </changeSet>

    <changeSet author="Rumyana Krumova" id="20190608-2">
        <insert schemaName="public"
                tableName="company">
            <column name="eik" value="5555"/>
            <column name="name" value="Zatvoreno EOOD"/>
            <column name="area" value="Kyustendil"/>
            <column name="city" value="Kyustendil"/>
            <column name="address" value="Dupnishko shose №20"/>
        </insert>
        <rollback/>
    </changeSet>
</databaseChangeLog>